TensorflowQianghuaXuexiChuyiFix1/README.md
TensorflowQianghuaXuexiChuyiFix1/__init__.py
TensorflowQianghuaXuexiChuyiFix1/__main__.py
TensorflowQianghuaXuexiChuyiFix1/file.epub
TensorflowQianghuaXuexiChuyiFix1/index.html
TensorflowQianghuaXuexiChuyiFix1/css/__init__.py
TensorflowQianghuaXuexiChuyiFix1/css/annotations.css
TensorflowQianghuaXuexiChuyiFix1/css/main.css
TensorflowQianghuaXuexiChuyiFix1/css/normalize.css
TensorflowQianghuaXuexiChuyiFix1/css/popup.css
TensorflowQianghuaXuexiChuyiFix1/font/__init__.py
TensorflowQianghuaXuexiChuyiFix1/font/fontello.eot
TensorflowQianghuaXuexiChuyiFix1/font/fontello.svg
TensorflowQianghuaXuexiChuyiFix1/font/fontello.ttf
TensorflowQianghuaXuexiChuyiFix1/font/fontello.woff
TensorflowQianghuaXuexiChuyiFix1/img/__init__.py
TensorflowQianghuaXuexiChuyiFix1/img/annotator-glyph-sprite.png
TensorflowQianghuaXuexiChuyiFix1/img/annotator-icon-sprite.png
TensorflowQianghuaXuexiChuyiFix1/img/apple-touch-icon.png
TensorflowQianghuaXuexiChuyiFix1/img/cancelfullscreen.png
TensorflowQianghuaXuexiChuyiFix1/img/close.png
TensorflowQianghuaXuexiChuyiFix1/img/fullscreen.png
TensorflowQianghuaXuexiChuyiFix1/img/loader.gif
TensorflowQianghuaXuexiChuyiFix1/img/menu-icon.png
TensorflowQianghuaXuexiChuyiFix1/img/save.png
TensorflowQianghuaXuexiChuyiFix1/img/saved.png
TensorflowQianghuaXuexiChuyiFix1/img/settings-s.png
TensorflowQianghuaXuexiChuyiFix1/img/settings.png
TensorflowQianghuaXuexiChuyiFix1/img/star.png
TensorflowQianghuaXuexiChuyiFix1/js/__init__.py
TensorflowQianghuaXuexiChuyiFix1/js/epub.js
TensorflowQianghuaXuexiChuyiFix1/js/epub.min.js
TensorflowQianghuaXuexiChuyiFix1/js/epub.min.map
TensorflowQianghuaXuexiChuyiFix1/js/hooks.min.js
TensorflowQianghuaXuexiChuyiFix1/js/hooks.min.map
TensorflowQianghuaXuexiChuyiFix1/js/reader.js
TensorflowQianghuaXuexiChuyiFix1/js/reader.js.map
TensorflowQianghuaXuexiChuyiFix1/js/reader.min.js
TensorflowQianghuaXuexiChuyiFix1/js/reader.min.map
TensorflowQianghuaXuexiChuyiFix1/js/hooks/__init__.py
tensorflow_qianghua_xuexi_chuyi_fix1-2025.3.25.0.dist-info/METADATA
tensorflow_qianghua_xuexi_chuyi_fix1-2025.3.25.0.dist-info/WHEEL
tensorflow_qianghua_xuexi_chuyi_fix1-2025.3.25.0.dist-info/entry_points.txt
tensorflow_qianghua_xuexi_chuyi_fix1-2025.3.25.0.dist-info/top_level.txt
tensorflow_qianghua_xuexi_chuyi_fix1-2025.3.25.0.dist-info/RECORD
